Workbook

Sheet Parámetros
A1: Parámetros de la boleta de pago
A2: Texto en azul = dato que se escribe a mano. Texto en negro = fórmula. Todo el libro lee los valores desde esta hoja.
A4: Parámetro | B4: Valor | C4: Fuente | D4: Fecha de consulta
A5: RMV (S/) | B5: 1230 | C5: D.S. 015-2026-TR (El Peruano, 28/09/2026), vigente desde el 01/10/2026 | D5: 25/10/2026
A6: Porcentaje de asignación familiar | B6: 0.1 | C6: Ley 25129 (10% de la RMV) | D6: 25/10/2026
A7: Asignación familiar (S/) | B7: =B5*B6 -> 123 | C7: Fórmula: RMV × porcentaje | D7: —
A8: Tasa ONP | B8: 0.13 | C8: D.L. 19990 | D8: 25/10/2026
A9: Tasa EsSalud (empleador) | B9: 0.09 | C9: Ley 26790 | D9: 25/10/2026
A10: Recargo horas extras: primeras horas | B10: 0.25 | C10: Normas de jornada y sobretiempo (según guía) | D10: 25/10/2026
A11: Recargo horas extras: horas siguientes | B11: 0.35 | C11: Normas de jornada y sobretiempo (según guía) | D11: 25/10/2026
A12: Días del mes comercial | B12: 30 | C12: Convención de la guía (sueldo ÷ 30) | D12: 25/10/2026
A13: Horas por día | B13: 8 | C13: Convención de la guía (valor hora = sueldo ÷ 30 ÷ 8) | D13: 25/10/2026
A16: Tasas por AFP (diccionario: nombre → tasas)
A17: AFP | B17: Fondo | C17: Comisión | D17: Seguro | E17: Fuente | F17: Fecha de consulta
A18: AFP Ejemplo | B18: 0.1 | C18: 0.016 | D18: 0.0135 | E18: Valores de prueba de la guía (solo casos de prueba) | F18: 25/10/2026
A23: Filas amarillas: para agregar las AFP reales con los valores publicados por la SBS (anota la fuente y la fecha). Aún no se han llenado.

Sheet Boleta
A1: Boleta de ejemplo
A2: Cambia solo las celdas amarillas. Viene cargado el caso 3 como ejemplo de formato.
A4: DATOS DE ENTRADA
A5: Sueldo básico (S/) | B5: 3000
A6: Días laborados (1 a 30) | B6: 30
A7: ¿Tiene hijos? (Sí / No) | B7: Sí
A8: Sistema de pensiones (ONP / AFP) | B8: AFP
A9: AFP (solo si el sistema es AFP) | B9: AFP Ejemplo
A10: Horas extras al 25% | B10: 4
A11: Horas extras al 35% | B11: 4
A12: Adelantos (S/) | B12: 200
A14: CÁLCULO
A15: REMUNERACIONES | B15: Monto (S/)
A16: Valor hora (sin redondear, solo auxiliar) | B16: =B5/Parámetros!B12/Parámetros!B13 -> 12.5
A17: Sueldo computable | B17: =ROUND(B5/Parámetros!B12*B6,2) -> 3000
A18: Asignación familiar | B18: =IF(B7="Sí",ROUND(Parámetros!B7,2),0) -> 123
A19: Horas extras 25% | B19: =ROUND(B16*(1+Parámetros!B10)*B10,2) -> 62.5
A20: Horas extras 35% | B20: =ROUND(B16*(1+Parámetros!B11)*B11,2) -> 67.5
A21: Total remuneraciones | B21: =SUM(B17:B20) -> 3253
A23: RETENCIONES / DESCUENTOS | B23: Monto (S/)
A24: ONP | B24: =IF(B8="ONP",ROUND(B21*Parámetros!B8,2),0) -> 0
A25: AFP fondo | B25: =IF(B8="AFP",ROUND(B21*INDEX(Parámetros!$B$18:$B$22,MATCH(B9,Parámetros!$A$18:$A$22,0)),2),0) -> 325.3
A26: AFP comisión | B26: =IF(B8="AFP",ROUND(B21*INDEX(Parámetros!$C$18:$C$22,MATCH(B9,Parámetros!$A$18:$A$22,0)),2),0) -> 52.05
A27: AFP seguro | B27: =IF(B8="AFP",ROUND(B21*INDEX(Parámetros!$D$18:$D$22,MATCH(B9,Parámetros!$A$18:$A$22,0)),2),0) -> 43.92
A28: Adelantos | B28: =B12 -> 200
A29: Total descuentos | B29: =SUM(B24:B28) -> 621.27
A31: APORTACIONES DEL EMPLEADOR | B31: Monto (S/)
A32: EsSalud (9%) | B32: =ROUND(B21*Parámetros!B9,2) -> 292.77
A34: NETO A PAGAR (S/) | B34: =B21-B29 -> 2631.73
A35: Costo total para el empleador (remuneraciones + EsSalud) | B35: =B21+B32 -> 3545.77
A36: % del costo que llega al trabajador como neto | B36: =B34/B35 -> 0.74221678

Sheet Casos
A1: Casos de prueba (control cruzado app ↔ Excel)
A2: Cada fila es un caso completo con las mismas reglas de la hoja Boleta. Después de correr el caso en la app, escribe su neto en la columna X (azul): la columna Y muestra la diferencia.
A5: Caso | B5: Sueldo básico | C5: Días | D5: ¿Hijos? | E5: Sistema | F5: AFP | G5: H.E. 25% | H5: H.E. 35% | I5: Adelantos | J5: Sueldo computable | K5: Asignación familiar | L5: H.E. 25% (S/) | M5: H.E. 35% (S/) | N5: Total remuneraciones | O5: ONP | P5: AFP fondo | Q5: AFP comisión | R5: AFP seguro | S5: Total descuentos | T5: Neto a pagar | U5: EsSalud (empleador) | V5: Neto según la guía | W5: ¿Coincide con la guía? | X5: Neto en la app | Y5: Diferencia app − Excel
A6: Caso 1 | B6: 2500 | C6: 30 | D6: No | E6: ONP | G6: 0 | H6: 0 | I6: 0 | J6: =IF($B6="","",ROUND(B6/Parámetros!$B$12*C6,2)) -> 2500 | K6: =IF($B6="","",IF(D6="Sí",ROUND(Parámetros!$B$7,2),0)) -> 0 | L6: =IF($B6="","",ROUND(B6/Parámetros!$B$12/Parámetros!$B$13*(1+Parámetros!$B$10)*G6,2)) -> 0 | M6: =IF($B6="","",ROUND(B6/Parámetros!$B$12/Parámetros!$B$13*(1+Parámetros!$B$11)*H6,2)) -> 0 | N6: =IF($B6="","",SUM(J6:M6)) -> 2500 | O6: =IF($B6="","",IF(E6="ONP",ROUND(N6*Parámetros!$B$8,2),0)) -> 325 | P6: =IF($B6="","",IF(E6="AFP",ROUND(N6*INDEX(Parámetros!$B$18:$B$22,MATCH(F6,Parámetros!$A$18:$A$22,0)),2),0)) -> 0 | Q6: =IF($B6="","",IF(E6="AFP",ROUND(N6*INDEX(Parámetros!$C$18:$C$22,MATCH(F6,Parámetros!$A$18:$A$22,0)),2),0)) -> 0 | R6: =IF($B6="","",IF(E6="AFP",ROUND(N6*INDEX(Parámetros!$D$18:$D$22,MATCH(F6,Parámetros!$A$18:$A$22,0)),2),0)) -> 0 | S6: =IF($B6="","",SUM(O6:R6)+I6) -> 325 | T6: =IF($B6="","",N6-S6) -> 2175 | U6: =IF($B6="","",ROUND(N6*Parámetros!$B$9,2)) -> 225 | V6: 2175 | W6: =IF(V6="","sin dato en la guía",IF(ROUND(T6-V6,2)=0,"Sí","NO")) -> Sí | Y6: =IF(X6="","",ROUND(X6-T6,2))
A7: Caso 2 | B7: 1800 | C7: 27 | D7: Sí | E7: ONP | G7: 0 | H7: 0 | I7: 0 | J7: =IF($B7="","",ROUND(B7/Parámetros!$B$12*C7,2)) -> 1620 | K7: =IF($B7="","",IF(D7="Sí",ROUND(Parámetros!$B$7,2),0)) -> 123 | L7: =IF($B7="","",ROUND(B7/Parámetros!$B$12/Parámetros!$B$13*(1+Parámetros!$B$10)*G7,2)) -> 0 | M7: =IF($B7="","",ROUND(B7/Parámetros!$B$12/Parámetros!$B$13*(1+Parámetros!$B$11)*H7,2)) -> 0 | N7: =IF($B7="","",SUM(J7:M7)) -> 1743 | O7: =IF($B7="","",IF(E7="ONP",ROUND(N7*Parámetros!$B$8,2),0)) -> 226.59 | P7: =IF($B7="","",IF(E7="AFP",ROUND(N7*INDEX(Parámetros!$B$18:$B$22,MATCH(F7,Parámetros!$A$18:$A$22,0)),2),0)) -> 0 | Q7: =IF($B7="","",IF(E7="AFP",ROUND(N7*INDEX(Parámetros!$C$18:$C$22,MATCH(F7,Parámetros!$A$18:$A$22,0)),2),0)) -> 0 | R7: =IF($B7="","",IF(E7="AFP",ROUND(N7*INDEX(Parámetros!$D$18:$D$22,MATCH(F7,Parámetros!$A$18:$A$22,0)),2),0)) -> 0 | S7: =IF($B7="","",SUM(O7:R7)+I7) -> 226.59 | T7: =IF($B7="","",N7-S7) -> 1516.41 | U7: =IF($B7="","",ROUND(N7*Parámetros!$B$9,2)) -> 156.87 | V7: 1516.41 | W7: =IF(V7="","sin dato en la guía",IF(ROUND(T7-V7,2)=0,"Sí","NO")) -> Sí | Y7: =IF(X7="","",ROUND(X7-T7,2))
A8: Caso 3 | B8: 3000 | C8: 30 | D8: Sí | E8: AFP | F8: AFP Ejemplo | G8: 4 | H8: 4 | I8: 200 | J8: =IF($B8="","",ROUND(B8/Parámetros!$B$12*C8,2)) -> 3000 | K8: =IF($B8="","",IF(D8="Sí",ROUND(Parámetros!$B$7,2),0)) -> 123 | L8: =IF($B8="","",ROUND(B8/Parámetros!$B$12/Parámetros!$B$13*(1+Parámetros!$B$10)*G8,2)) -> 62.5 | M8: =IF($B8="","",ROUND(B8/Parámetros!$B$12/Parámetros!$B$13*(1+Parámetros!$B$11)*H8,2)) -> 67.5 | N8: =IF($B8="","",SUM(J8:M8)) -> 3253 | O8: =IF($B8="","",IF(E8="ONP",ROUND(N8*Parámetros!$B$8,2),0)) -> 0 | P8: =IF($B8="","",IF(E8="AFP",ROUND(N8*INDEX(Parámetros!$B$18:$B$22,MATCH(F8,Parámetros!$A$18:$A$22,0)),2),0)) -> 325.3 | Q8: =IF($B8="","",IF(E8="AFP",ROUND(N8*INDEX(Parámetros!$C$18:$C$22,MATCH(F8,Parámetros!$A$18:$A$22,0)),2),0)) -> 52.05 | R8: =IF($B8="","",IF(E8="AFP",ROUND(N8*INDEX(Parámetros!$D$18:$D$22,MATCH(F8,Parámetros!$A$18:$A$22,0)),2),0)) -> 43.92 | S8: =IF($B8="","",SUM(O8:R8)+I8) -> 621.27 | T8: =IF($B8="","",N8-S8) -> 2631.73 | U8: =IF($B8="","",ROUND(N8*Parámetros!$B$9,2)) -> 292.77 | V8: 2631.73 | W8: =IF(V8="","sin dato en la guía",IF(ROUND(T8-V8,2)=0,"Sí","NO")) -> Sí | Y8: =IF(X8="","",ROUND(X8-T8,2))
A9: Caso 4 (evalúa el docente) | B9: 4200 | C9: 24 | D9: Sí | E9: AFP | F9: AFP Ejemplo | G9: 2 | H9: 2 | I9: 100 | J9: =IF($B9="","",ROUND(B9/Parámetros!$B$12*C9,2)) -> 3360 | K9: =IF($B9="","",IF(D9="Sí",ROUND(Parámetros!$B$7,2),0)) -> 123 | L9: =IF($B9="","",ROUND(B9/Parámetros!$B$12/Parámetros!$B$13*(1+Parámetros!$B$10)*G9,2)) -> 43.75 | M9: =IF($B9="","",ROUND(B9/Parámetros!$B$12/Parámetros!$B$13*(1+Parámetros!$B$11)*H9,2)) -> 47.25 | N9: =IF($B9="","",SUM(J9:M9)) -> 3574 | O9: =IF($B9="","",IF(E9="ONP",ROUND(N9*Parámetros!$B$8,2),0)) -> 0 | P9: =IF($B9="","",IF(E9="AFP",ROUND(N9*INDEX(Parámetros!$B$18:$B$22,MATCH(F9,Parámetros!$A$18:$A$22,0)),2),0)) -> 357.4 | Q9: =IF($B9="","",IF(E9="AFP",ROUND(N9*INDEX(Parámetros!$C$18:$C$22,MATCH(F9,Parámetros!$A$18:$A$22,0)),2),0)) -> 57.18 | R9: =IF($B9="","",IF(E9="AFP",ROUND(N9*INDEX(Parámetros!$D$18:$D$22,MATCH(F9,Parámetros!$A$18:$A$22,0)),2),0)) -> 48.25 | S9: =IF($B9="","",SUM(O9:R9)+I9) -> 562.83 | T9: =IF($B9="","",N9-S9) -> 3011.17 | U9: =IF($B9="","",ROUND(N9*Parámetros!$B$9,2)) -> 321.66 | W9: =IF(V9="","sin dato en la guía",IF(ROUND(T9-V9,2)=0,"Sí","NO")) -> sin dato en la guía | Y9: =IF(X9="","",ROUND(X9-T9,2))
A10: Caso propio (oferta laboral real) | J10: =IF($B10="","",ROUND(B10/Parámetros!$B$12*C10,2)) | K10: =IF($B10="","",IF(D10="Sí",ROUND(Parámetros!$B$7,2),0)) | L10: =IF($B10="","",ROUND(B10/Parámetros!$B$12/Parámetros!$B$13*(1+Parámetros!$B$10)*G10,2)) | M10: =IF($B10="","",ROUND(B10/Parámetros!$B$12/Parámetros!$B$13*(1+Parámetros!$B$11)*H10,2)) | N10: =IF($B10="","",SUM(J10:M10)) | O10: =IF($B10="","",IF(E10="ONP",ROUND(N10*Parámetros!$B$8,2),0)) | P10: =IF($B10="","",IF(E10="AFP",ROUND(N10*INDEX(Parámetros!$B$18:$B$22,MATCH(F10,Parámetros!$A$18:$A$22,0)),2),0)) | Q10: =IF($B10="","",IF(E10="AFP",ROUND(N10*INDEX(Parámetros!$C$18:$C$22,MATCH(F10,Parámetros!$A$18:$A$22,0)),2),0)) | R10: =IF($B10="","",IF(E10="AFP",ROUND(N10*INDEX(Parámetros!$D$18:$D$22,MATCH(F10,Parámetros!$A$18:$A$22,0)),2),0)) | S10: =IF($B10="","",SUM(O10:R10)+I10) | T10: =IF($B10="","",N10-S10) | U10: =IF($B10="","",ROUND(N10*Parámetros!$B$9,2)) | W10: =IF(V10="","sin dato en la guía",IF(ROUND(T10-V10,2)=0,"Sí","NO")) -> sin dato en la guía | Y10: =IF(X10="","",ROUND(X10-T10,2))
A12: Fuente de la columna V: guía del curso, casos 1 a 3 (azul = dato copiado de la guía). El caso 4 no trae respuesta: lo revisa el docente. El caso propio se completa con el sueldo de una oferta real (guardar enlace y fecha en la tabla de fuentes).

Sheet Explicación
A1: Explicación de cada fórmula
A2: Pensada para alguien que no sabe contabilidad. Los números de ejemplo y el resultado se leen de la fila del Caso 3 de la hoja Casos (sueldo S/ 3,000, 30 días, con hijos, AFP, 4+4 horas extras, adelanto S/ 200).
A4: Concepto | B4: Qué es, en palabras | C4: Fórmula (en palabras) | D4: Ejemplo numérico (caso 3) | E4: Resultado en Excel (S/)
A5: Sueldo computable | B5: La parte del sueldo que realmente se ganó en el mes, según los días que se trabajó. | C5: Sueldo básico ÷ 30 × días laborados, redondeado a 2 decimales. | D5: 3,000 ÷ 30 × 30 = 3,000.00 | E5: =Casos!J8 -> 3000
A6: Asignación familiar | B6: Un monto fijo que recibe quien tiene hijos. No depende de los días trabajados. | C6: Si tiene hijos: 10% de la RMV (sueldo mínimo legal). Si no, 0. | D6: 10% × 1,230 = 123.00 | E6: =Casos!K8 -> 123
A7: Valor hora | B7: Cuánto vale una hora normal de trabajo. Sirve para calcular las horas extras. | C7: Sueldo básico ÷ 30 ÷ 8. No se redondea (solo se usa para calcular). | D7: 3,000 ÷ 30 ÷ 8 = 12.50 | E7: =Boleta!B16 -> 12.5
A8: Horas extras al 25% | B8: Horas trabajadas de más. Se pagan con un recargo del 25% sobre el valor hora. | C8: Valor hora × 1.25 × número de horas. | D8: 12.50 × 1.25 × 4 = 62.50 | E8: =Casos!L8 -> 62.5
A9: Horas extras al 35% | B9: Horas de más a partir de cierto punto, con recargo del 35%. | C9: Valor hora × 1.35 × número de horas. | D9: 12.50 × 1.35 × 4 = 67.50 | E9: =Casos!M8 -> 67.5
A10: Total remuneraciones | B10: Todo lo que el trabajador gana en el mes antes de descuentos (también se llama sueldo bruto del mes). | C10: Suma de sueldo computable, asignación familiar y horas extras. | D10: 3,000 + 123 + 62.50 + 67.50 = 3,253.00 | E10: =Casos!N8 -> 3253
A11: ONP | B11: Aporte al sistema público de pensiones. Se descuenta al trabajador si está en la ONP. | C11: 13% del total de remuneraciones. Si está en AFP, es 0. | D11: En el caso 3 es AFP, por eso 0.00 (con ONP serían 3,253 × 13% = 422.89) | E11: =Casos!O8 -> 0
A12: AFP fondo | B12: Parte del descuento que va a la cuenta de ahorro personal del trabajador para su jubilación. | C12: Total de remuneraciones × tasa de fondo de su AFP. | D12: 3,253 × 10% = 325.30 | E12: =Casos!P8 -> 325.3
A13: AFP comisión | B13: Lo que cobra la AFP por administrar la cuenta. | C13: Total de remuneraciones × tasa de comisión, redondeado a 2 decimales. | D13: 3,253 × 1.60% = 52.048 → 52.05 | E13: =Casos!Q8 -> 52.05
A14: AFP seguro | B14: Seguro de invalidez y sobrevivencia que cubre la AFP. | C14: Total de remuneraciones × tasa de seguro, redondeado a 2 decimales. | D14: 3,253 × 1.35% = 43.9155 → 43.92 | E14: =Casos!R8 -> 43.92
A15: Adelantos | B15: Dinero que la empresa ya le entregó al trabajador durante el mes. | C15: Se resta tal cual, sin porcentaje. | D15: 200.00 | E15: =Casos!I8 -> 200
A16: Total descuentos | B16: Todo lo que se le resta al trabajador: su pensión (ONP o AFP) y los adelantos. | C16: Pensión (ONP o las tres de AFP) + adelantos. | D16: 325.30 + 52.05 + 43.92 + 200.00 = 621.27 | E16: =Casos!S8 -> 621.27
A17: Neto a pagar | B17: El dinero que realmente llega al bolsillo del trabajador. | C17: Total remuneraciones − total descuentos. | D17: 3,253.00 − 621.27 = 2,631.73 | E17: =Casos!T8 -> 2631.73
A18: EsSalud (empleador) | B18: Aporte de salud que paga la empresa por el trabajador. No se descuenta al trabajador: es un costo extra de la empresa. | C18: 9% del total de remuneraciones. | D18: 3,253 × 9% = 292.77 | E18: =Casos!U8 -> 292.77
A19: Redondeo | B19: Para que todos obtengan el mismo resultado, cada concepto se redondea a 2 decimales y recién después se suman. | C19: ROUND(valor; 2) en cada concepto, nunca sobre el total. | D19: 52.048 → 52.05
